Metadata-Version: 1.0
Name: dsnd-calc
Version: 0.1
Summary: Gaussian distributions
Home-page: UNKNOWN
Author: UNKNOWN
Author-email: farouk.sallak@outlook.com
License: UNKNOWN
Platform: UNKNOWN
